[
  {
    "codigoChave": "BIBLIO01",
    "descricaoChave": "Chave Geral Biblioteca",
    "solicitante": {
      "nome": "Pedro Geremias",
      "vinculo": "servidor",
      "cursoSetor": "CC",
      "telefone": "44 44 44"
    },
    "dataHoraRetirada": "2025-07-28T06:42:55.663Z"
  },
  {
    "codigoChave": "LABINF03",
    "descricaoChave": "Laboratório de Informática 03",
    "solicitante": {
      "nome": "Jao Pedro",
      "vinculo": "aluno",
      "cursoSetor": "CC",
      "telefone": "46 66666"
    },
    "dataHoraRetirada": "2025-07-28T16:26:38.488Z"
  },
  {
    "codigoChave": "AUDITORIO",
    "descricaoChave": "Auditório Principal",
    "solicitante": {
      "nome": "abc",
      "vinculo": "aluno",
      "cursoSetor": "CC",
      "telefone": "4444444"
    },
    "dataHoraRetirada": "2025-07-31T23:56:29.093Z"
  }
]